{"trial_id": "0019", "hyperparameters": {"space": [{"class_name": "Choice", "config": {"name": "units", "default": 32, "conditions": [], "values": [32, 64, 128, 256, 512], "ordered": true}}, {"class_name": "Choice", "config": {"name": "learning_rate", "default": 0.001, "conditions": [], "values": [0.001, 0.0001, 1e-05], "ordered": true}}, {"class_name": "Choice", "config": {"name": "batch_size", "default": 8, "conditions": [], "values": [8, 16, 32], "ordered": true}}], "values": {"units": 128, "learning_rate": 0.001, "batch_size": 16}}, "metrics": {"metrics": {"test_loss": {"direction": "min", "observations": [{"value": [34.75975704193115], "step": 0}]}, "test_mae": {"direction": "min", "observations": [{"value": [4.770111513137818], "step": 0}]}, "test_rmse": {"direction": "min", "observations": [{"value": [5.524413585662842], "step": 0}]}, "test_r2": {"direction": "min", "observations": [{"value": [-0.06682851314544677], "step": 0}]}}}, "score": 34.75975704193115, "best_step": 0, "status": "COMPLETED", "message": null}